roiloc/__init__.py
roiloc/_cache.py
roiloc/location.py
roiloc/locator.py
roiloc/registration.py
roiloc/roiloc.py
roiloc/sanitychecks.py
roiloc/template.py
roiloc/MNI/COPYING
roiloc/MNI/cerebra/CerebrA_LabelDetails.csv
roiloc/MNI/cerebra/mni_icbm152_CerebrA_tal_nlin_sym_09c.nii
roiloc/MNI/icbm152/mni_icbm152_t1_tal_nlin_sym_09c.nii
roiloc/MNI/icbm152/mni_icbm152_t1_tal_nlin_sym_09c_mask.nii
roiloc/MNI/icbm152/mni_icbm152_t1bet_tal_nlin_sym_09c.nii
roiloc/MNI/icbm152/mni_icbm152_t2_tal_nlin_sym_09c.nii
roiloc/MNI/icbm152/mni_icbm152_t2bet_tal_nlin_sym_09c.nii
roiloc-0.4.1.dist-info/METADATA
roiloc-0.4.1.dist-info/WHEEL
roiloc-0.4.1.dist-info/entry_points.txt
roiloc-0.4.1.dist-info/licenses/LICENSE
roiloc-0.4.1.dist-info/RECORD
