Metadata-Version: 2.3
Name: roiloc
Version: 0.4.1
Summary: A simple package to center and crop T1w & T2w MRIs around a given region of interest by its name.
Project-URL: homepage, https://hippomnesis.dev
Project-URL: repository, https://github.com/clementpoiret/ROILoc
Author-email: Clément POIRET <poiret.clement@outlook.fr>
License: MIT License
License-File: LICENSE
Keywords: brain,mri,registration,t1w,t2w
Classifier: Development Status :: 4 - Beta
Classifier: License :: OSI Approved :: MIT License
Classifier: Topic :: Scientific/Engineering :: Bio-Informatics
Classifier: Topic :: Scientific/Engineering :: Image Processing
Requires-Python: >=3.9
Requires-Dist: antspyx>=0.5.0
Requires-Dist: pandas>=2.0.0
Requires-Dist: rich>=11.0.0
